{
  "db_name": "PostgreSQL",
  "query": "SELECT id, eve_character_id FROM eve_character WHERE eve_character_id = ANY($1)",
  "describe": {
    "columns": [
      {
        "ordinal": 0,
        "name": "id",
        "type_info": "Uuid"
      },
      {
        "ordinal": 1,
        "name": "eve_character_id",
        "type_info": "Int8"
      }
    ],
    "parameters": {
      "Left": [
        "Int8Array"
      ]
    },
    "nullable": [
      false,
      false
    ]
  },
  "hash": "00804571d1f1cf4387ee86f1a505888c3e4584b2039385862e5830c8147880bc"
}
